{
    "KVCT": {
        "text": 0,
        "display": false
    },
    "KPKV": {
        "text": 1,
        "display": false
    },
    "KPSX": {
        "text": 2,
        "display": false
    },
    "KBYY": {
        "text": 3,
        "display": false
    },
    "KLBX": {
        "text": 4,
        "display": false
    },
    "KGLS": {
        "text": "Galveston",
        "display": true
    },
    "KLVJ": {
        "text": 6,
        "display": false
    },
    "KEFD": {
        "text": "Ellington",
        "display": false
    },
    "KHOU": {
        "text": "Hobby",
        "display": true
    },
    "KSGR": {
        "text": 9,
        "display": false
    },
    "KARM": {
        "text": 10,
        "display": false
    },
    "KELA": {
        "text": 11,
        "display": false
    },
    "KTME": {
        "text": 12,
        "display": false
    },
    "K11R": {
        "text": 13,
        "display": false
    },
    "KCLL": {
        "text": 14,
        "display": true
    },
    "KLXY": {
        "text": 15,
        "display": false
    },
    "KPSN": {
        "text": 16,
        "display": false
    },
    "KDKR": {
        "text": "Crockett",
        "display": true
    },
    "KUTS": {
        "text": "Huntsville",
        "display": false
    },
    "KCXO": {
        "text": "Conroe",
        "display": true
    },
    "KDWH": {
        "text": "Hooks",
        "display": true
    },
    "KIAH": {
        "text": "Intercontinental",
        "display": true
    },
    "KT78": {
        "text": 22,
        "display": false
    },
    "KBMT": {
        "text": 23,
        "display": false
    },
    "KBPT": {
        "text": 24,
        "display": false
    },
    "KORG": {
        "text": 25,
        "display": false
    },
    "KUXL": {
        "text": 26,
        "display": false
    },
    "KLCH": {
        "text": "Lake Charles",
        "display": true
    },
    "KCWF": {
        "text": 28,
        "display": false
    },
    "K3R7": {
        "text": 29,
        "display": false
    },
    "KLFT": {
        "text": 30,
        "display": false
    },
    "KHUM": {
        "text": 31,
        "display": true
    },
    "KAPS": {
        "text": "Port of South Louisiana",
        "display": false
    },
    "KREG": {
        "text": 33,
        "display": false
    },
    "KBTR": {
        "text": 34,
        "display": false
    },
    "KHZR": {
        "text": 35,
        "display": false
    },
    "KOPL": {
        "text": 36,
        "display": false
    },
    "KACP": {
        "text": 37,
        "display": false
    },
    "KPOE": {
        "text": 38,
        "display": false
    },
    "KDRI": {
        "text": "DeRidder",
        "display": false
    },
    "KJAS": {
        "text": 40,
        "display": false
    },
    "KLFK": {
        "text": "Lufkin",
        "display": false
    },
    "KOCH": {
        "text": "Nacogdoches",
        "display": true
    },
    "KJSO": {
        "text": 43,
        "display": false
    },
    "KRFI": {
        "text": 44,
        "display": false
    },
    "K4F2": {
        "text": 45,
        "display": false
    },
    "K3F3": {
        "text": 46,
        "display": false
    },
    "KIER": {
        "text": 47,
        "display": false
    },
    "KAEX": {
        "text": 48,
        "display": false
    },
    "KHEZ": {
        "text": 49,
        "display": false
    }
}
